{"imageUrl":"https://upload.wikimedia.org/wikipedia/commons/9/9b/Eastern_Bluebird-27527-2.jpg","description":"Birds (Aves), also known as avian dinosaurs,[3] are a group of endothermic vertebrates, characterised by feathers, toothless beaked jaws, the laying of hard-shelled eggs, a high metabolic rate, a four-chambered heart, and a lightweight but strong skeleton. Birds live worldwide and range in size from the 5 cm (2 in) bee hummingbird to the 2.75 m (9 ft) ostrich. They rank as the class of tetrapods with the most living species, at approximately ten thousand,","age":"2","price":"100","name":"Bird","id":"Bird"}